batterylearn/__init__.py
batterylearn/__main__.py
batterylearn/base.py
batterylearn/cli.py
batterylearn/controls/__init__.py
batterylearn/controls/filters.py
batterylearn/elements/__init__.py
batterylearn/elements/elements.py
batterylearn/models/__init__.py
batterylearn/models/battery.py
batterylearn/simulations/__init__.py
batterylearn/simulations/learns.py
batterylearn/simulations/simulations.py
batterylearn/utilities/__init__.py
batterylearn/utilities/solvers.py
batterylearn-1.1.3.dist-info/LICENSE
batterylearn-1.1.3.dist-info/METADATA
batterylearn-1.1.3.dist-info/WHEEL
batterylearn-1.1.3.dist-info/entry_points.txt
batterylearn-1.1.3.dist-info/top_level.txt
batterylearn-1.1.3.dist-info/RECORD
