Metadata-Version: 2.1
Name: batterylearn
Version: 1.1.3
Summary: Python based energy storage simulator
Home-page: https://github.com/tonylee2016/batterylearn/
Author: tonylee2016
License: UNKNOWN
Platform: UNKNOWN
Requires-Dist: numpy
Requires-Dist: scipy (~=1.9)
Requires-Dist: setuptools (~=49.6.0)
Requires-Dist: matplotlib (~=3.3.4)
Requires-Dist: pandas (~=1.4.2)
Requires-Dist: pytest (~=7.1.2)
Requires-Dist: sympy (~=1.10.1)
Requires-Dist: tabulate (~=0.8.9)
Requires-Dist: schemdraw (==0.14)
Requires-Dist: sklearn
Requires-Dist: openpyxl
Provides-Extra: test
Requires-Dist: pytest ; extra == 'test'
Requires-Dist: coverage ; extra == 'test'
Requires-Dist: flake8 ; extra == 'test'
Requires-Dist: black ; extra == 'test'
Requires-Dist: isort ; extra == 'test'
Requires-Dist: pytest-cov ; extra == 'test'
Requires-Dist: codecov ; extra == 'test'
Requires-Dist: mypy ; extra == 'test'
Requires-Dist: gitchangelog ; extra == 'test'
Requires-Dist: mkdocs ; extra == 'test'
